django_silly_stripe/__init__.py
django_silly_stripe/admin.py
django_silly_stripe/conf.py
django_silly_stripe/helpers.py
django_silly_stripe/models.py
django_silly_stripe/serializers.py
django_silly_stripe/urls.py
django_silly_stripe/views.py
django_silly_stripe/views_api.py
django_silly_stripe/views_classic.py
django_silly_stripe/migrations/0001_initial.py
django_silly_stripe/migrations/0002_alter_customer_user.py
django_silly_stripe/migrations/0003_remove_customer_stripe_id_alter_customer_id.py
django_silly_stripe/migrations/0004_customer_email.py
django_silly_stripe/migrations/0005_customer_name.py
django_silly_stripe/migrations/0006_product_price.py
django_silly_stripe/migrations/0007_price_metadata.py
django_silly_stripe/migrations/0008_subscription.py
django_silly_stripe/migrations/0009_subscription_end_time_subscription_start_time_and_more.py
django_silly_stripe/migrations/0010_alter_subscription_end_time_and_more.py
django_silly_stripe/migrations/0011_subscription_cancel_at_period_end.py
django_silly_stripe/migrations/__init__.py
django_silly_stripe/templates/__init__.py
django_silly_stripe/templates/admin/__init__.py
django_silly_stripe/templates/admin/base.html
django_silly_stripe-1.0.4.dist-info/LICENSE.md
django_silly_stripe-1.0.4.dist-info/METADATA
django_silly_stripe-1.0.4.dist-info/WHEEL
django_silly_stripe-1.0.4.dist-info/top_level.txt
django_silly_stripe-1.0.4.dist-info/RECORD
